[
  {
    "run_id": "012c18e9",
    "date": "2026-05-23T23:58:31.365415",
    "skill_id": 1,
    "skill_name": "Technical Crawl Audit",
    "score": 100,
    "issues_found": 0,
    "issues_critical": 0,
    "duration_s": 11,
    "status": "completed",
    "notes": "Group 3 | skill 1/23",
    "cycle": 1
  },
  {
    "run_id": "9e672fb9",
    "date": "2026-05-25T00:00:12.994042",
    "skill_id": 2,
    "skill_name": "Robots.txt & Sitemap Validation",
    "score": 95,
    "issues_found": 1,
    "issues_critical": 0,
    "duration_s": 6,
    "status": "completed",
    "notes": "Group 3 | skill 2/23",
    "cycle": 1
  },
  {
    "run_id": "92722d1d",
    "date": "2026-05-26T00:06:21.863512",
    "skill_id": 3,
    "skill_name": "Canonical & Redirects Audit",
    "score": 100,
    "issues_found": 0,
    "issues_critical": 0,
    "duration_s": 7,
    "status": "completed",
    "notes": "Group 3 | skill 3/23",
    "cycle": 1
  },
  {
    "run_id": "e979fd88",
    "date": "2026-05-27T00:05:16.314780",
    "skill_id": 4,
    "skill_name": "Structured Data Audit",
    "score": 65,
    "issues_found": 7,
    "issues_critical": 0,
    "duration_s": 7,
    "status": "completed",
    "notes": "Group 3 | skill 4/23",
    "cycle": 1
  },
  {
    "run_id": "e18e69b9",
    "date": "2026-05-28T00:00:42.644319",
    "skill_id": 5,
    "skill_name": "Core Web Vitals",
    "score": 46,
    "issues_found": 4,
    "issues_critical": 4,
    "duration_s": 132,
    "status": "completed",
    "notes": "Group 3 | skill 5/23",
    "cycle": 1
  }
]